pyckson/__init__.py
pyckson/const.py
pyckson/decorators.py
pyckson/defaults.py
pyckson/helpers.py
pyckson/json.py
pyckson/parser.py
pyckson/providers.py
pyckson/serializer.py
pyckson/dates/__init__.py
pyckson/dates/arrow.py
pyckson/dates/helpers.py
pyckson/dates/model.py
pyckson/dates/raw_formatter.py
pyckson/model/__init__.py
pyckson/model/builder.py
pyckson/model/helpers.py
pyckson/model/model.py
pyckson/model/union.py
pyckson/parsers/__init__.py
pyckson/parsers/advanced.py
pyckson/parsers/base.py
pyckson/parsers/provider.py
pyckson/serializers/__init__.py
pyckson/serializers/advanced.py
pyckson/serializers/base.py
pyckson/serializers/provider.py
Pyckson-1.14.0.dist-info/AUTHORS
Pyckson-1.14.0.dist-info/LICENSE
Pyckson-1.14.0.dist-info/METADATA
Pyckson-1.14.0.dist-info/WHEEL
Pyckson-1.14.0.dist-info/top_level.txt
Pyckson-1.14.0.dist-info/RECORD
