Metadata-Version: 2.1
Name: Pyckson
Version: 1.14.0
Summary: A minimalist python object mapper
Home-page: https://github.com/antidot/Pyckson
Author: Jean Giard
Author-email: opensource@antidot.net
License: LGPL-2.1-or-later
Keywords: pyckson json
License-File: LICENSE
License-File: AUTHORS
Requires-Dist: arrow
